flake8_unfinished.py
flake8_unfinished-1.2.0.dist-info/LICENSE
flake8_unfinished-1.2.0.dist-info/METADATA
flake8_unfinished-1.2.0.dist-info/WHEEL
flake8_unfinished-1.2.0.dist-info/entry_points.txt
flake8_unfinished-1.2.0.dist-info/top_level.txt
flake8_unfinished-1.2.0.dist-info/RECORD
